{
  "generated_at": "2026-05-28T12:02:00.932735",
  "news": [
    {
      "bu": "润滑油事业部",
      "title": "ExxonMobil完成新加坡Group II基础油产能扩建",
      "date": "2026-05-26"
    },
    {
      "bu": "常州锂源事业部",
      "title": "磷酸铁锂高端扩产潮来袭，规划总产能380万吨/年",
      "date": "2026-05-26"
    },
    {
      "bu": "山东美多事业部",
      "title": "格林美二度冲刺港股IPO，负债率攀升至66%",
      "date": "2026-05-26"
    },
    {
      "bu": "铂源催化事业部",
      "title": "科研端低铂催化剂与PEM铂碳催化剂量产同步突破",
      "date": "2026-05-26"
    },
    {
      "bu": "法恩莱特事业部",
      "title": "CIBF2026开幕，头部电解液企业聚焦四大技术方向",
      "date": "2026-05-26"
    }
  ]
}