{
  "date": "2026-04-12",
  "departments": {
    "lpsd": {
      "name": "龙蟠时代",
      "subtitle": "碳酸锂/氢氧化锂市场",
      "headline": "碳酸锂价格16.20万元/吨，市场震荡上行",
      "lead": "4月12日碳酸锂价格报16.20万元/吨左右，市场震荡上行。",
      "sections": {
        "原料价格": [
          {
            "title": "碳酸锂价格16.20万元/吨",
            "content": "4月12日报价约16.20万元/吨",
            "source": "市场数据",
            "date": "2026-04-12"
          }
        ]
      },
      "risk": "价格波动",
      "conclusion": "需求支撑价格上行",
      "sectionsByDim": {
        "topnews": [],
        "市场": [],
        "政策": [],
        "竞品": [],
        "前沿": [],
        "客户": [],
        "action": []
      }
    },
    "sjld": {
      "name": "三金锂电",
      "subtitle": "三元正极材料市场",
      "headline": "容百科技信披违规处罚持续发酵",
      "lead": "容百科技因与宁德时代重大合同信披不准确被罚450万元事件持续发酵。",
      "sections": {
        "竞品动态": [
          {
            "title": "容百科技信披违规被罚",
            "content": "容百科技因信披不准确被罚450万元，责任人共被罚500万元",
            "source": "蓝鲸新闻",
            "date": "2026-04-12"
          }
        ]
      },
      "risk": "合规风险",
      "conclusion": "信披合规重要性凸显",
      "sectionsByDim": {
        "topnews": [],
        "市场": [],
        "政策": [],
        "竞品": [],
        "前沿": [],
        "客户": [],
        "action": []
      }
    },
    "sdmd": {
      "name": "山东美多",
      "subtitle": "废旧动力电池回收",
      "headline": "电池回收新规正式施行",
      "lead": "《新能源汽车废旧动力电池回收和综合利用管理暂行办法》4月1日起正式施行。",
      "sections": {
        "行业政策": [
          {
            "title": "电池回收新规正式施行",
            "content": "4月1日起正式施行",
            "source": "政策文件",
            "date": "2026-04-01"
          }
        ]
      },
      "risk": "合规成本",
      "conclusion": "白名单优势明显",
      "sectionsByDim": {
        "topnews": [],
        "市场": [],
        "政策": [],
        "竞品": [],
        "前沿": [],
        "客户": [],
        "action": []
      }
    },
    "felt": {
      "name": "法恩莱特",
      "subtitle": "电解液市场",
      "headline": "六氟磷酸锂价格约11万元/吨",
      "lead": "六氟磷酸锂价格约11万元/吨，市场观望。",
      "sections": {
        "原料价格": [
          {
            "title": "六氟磷酸锂约11万元/吨",
            "content": "4月12日报价约11万元/吨",
            "source": "市场数据",
            "date": "2026-04-12"
          }
        ]
      },
      "risk": "价格承压",
      "conclusion": "需求一般",
      "sectionsByDim": {
        "topnews": [],
        "市场": [],
        "政策": [],
        "竞品": [],
        "前沿": [],
        "客户": [],
        "action": []
      }
    },
    "czly": {
      "name": "常州锂源",
      "subtitle": "磷酸铁锂正极材料市场",
      "headline": "磷酸铁锂市场稳定",
      "lead": "磷酸铁锂市场稳定运行。",
      "sections": {},
      "risk": "产能过剩",
      "conclusion": "头部企业稳定"
    },
    "kls": {
      "name": "可兰素",
      "subtitle": "车用尿素市场",
      "headline": "车用尿素市场平稳",
      "lead": "车用尿素市场平稳运行。",
      "sections": {},
      "risk": "价格波动",
      "conclusion": "需求稳定"
    },
    "lhy": {
      "name": "润滑油",
      "subtitle": "润滑油市场",
      "headline": "润滑油市场稳定",
      "lead": "润滑油市场稳定。",
      "sections": {},
      "risk": "需求波动",
      "conclusion": "国产替代空间大"
    },
    "bych": {
      "name": "铂源催化",
      "subtitle": "氢燃料电池催化剂市场",
      "headline": "铂金价格维持高位",
      "lead": "铂金价格维持高位。",
      "sections": {
        "贵金属行情": [
          {
            "title": "铂金价格高位",
            "content": "铂金价格维持高位",
            "source": "市场数据",
            "date": "2026-04-12"
          }
        ]
      },
      "risk": "成本压力",
      "conclusion": "氢能政策带来机遇",
      "sectionsByDim": {
        "topnews": [],
        "市场": [],
        "政策": [],
        "竞品": [],
        "前沿": [],
        "客户": [],
        "action": []
      }
    },
    "dhx": {
      "name": "迪克化学",
      "subtitle": "制动液/防冻液市场",
      "headline": "防冻液市场稳定",
      "lead": "防冻液市场稳定运行。",
      "sections": {},
      "risk": "原材料波动",
      "conclusion": "后市场空间广阔"
    }
  }
}